[{"OrderId":1,"ClientId":1,"Item":"Test order","IsCompleted":false},{"OrderId":2,"ClientId":1,"Item":"Test order","IsCompleted":false},{"OrderId":3,"ClientId":1,"Item":"Test order","IsCompleted":false},{"OrderId":4,"ClientId":1,"Item":"Test order","IsCompleted":false},{"OrderId":5,"ClientId":1,"Item":"Test order","IsCompleted":false},{"OrderId":6,"ClientId":1,"Item":"Test order","IsCompleted":false},{"OrderId":7,"ClientId":1,"Item":"Test order","IsCompleted":false},{"OrderId":8,"ClientId":1,"Item":"Test order","IsCompleted":false},{"OrderId":9,"ClientId":1,"Item":"Test order","IsCompleted":false}]